bat/__init__.py
bat/data_generator.py
bat/dataframe_cache.py
bat/dataframe_stats.py
bat/dataframe_to_matrix.py
bat/live_simulator.py
bat/log_to_dataframe.py
bat/log_to_sparkdf.py
bat/zeek_log_reader.py
bat/zeek_multi_log_reader.py
bat/utils/__init__.py
bat/utils/cache.py
bat/utils/compat.py
bat/utils/dir_watcher.py
bat/utils/file_storage.py
bat/utils/file_tailer.py
bat/utils/file_utils.py
bat/utils/geo_lookup.py
bat/utils/net_utils.py
bat/utils/ngrams.py
bat/utils/plot_utils.py
bat/utils/reverse_dns.py
bat/utils/signal_utils.py
bat/utils/vt_query.py
pyzeek/__init__.py
pyzeek/data_generator.py
pyzeek/dataframe_cache.py
pyzeek/dataframe_stats.py
pyzeek/dataframe_to_matrix.py
pyzeek/live_simulator.py
pyzeek/log_to_dataframe.py
pyzeek/log_to_sparkdf.py
pyzeek/zeek_log_reader.py
pyzeek/zeek_multi_log_reader.py
pyzeek/utils/__init__.py
pyzeek/utils/cache.py
pyzeek/utils/compat.py
pyzeek/utils/dir_watcher.py
pyzeek/utils/file_storage.py
pyzeek/utils/file_tailer.py
pyzeek/utils/file_utils.py
pyzeek/utils/geo_lookup.py
pyzeek/utils/net_utils.py
pyzeek/utils/ngrams.py
pyzeek/utils/plot_utils.py
pyzeek/utils/reverse_dns.py
pyzeek/utils/signal_utils.py
pyzeek/utils/vt_query.py
pyzeek-0.3.9.data/data/data/app_stats.log
pyzeek-0.3.9.data/data/data/conn.log
pyzeek-0.3.9.data/data/data/dhcp.log
pyzeek-0.3.9.data/data/data/dhcp.log.gz
pyzeek-0.3.9.data/data/data/dhcp_002.log
pyzeek-0.3.9.data/data/data/dhcp_002.log.gz
pyzeek-0.3.9.data/data/data/dns.log
pyzeek-0.3.9.data/data/data/files.log
pyzeek-0.3.9.data/data/data/ftp.log
pyzeek-0.3.9.data/data/data/http.log
pyzeek-0.3.9.data/data/data/http.log.gz
pyzeek-0.3.9.data/data/data/http_empty.log
pyzeek-0.3.9.data/data/data/notice.log
pyzeek-0.3.9.data/data/data/smtp.log
pyzeek-0.3.9.data/data/data/ssl.log
pyzeek-0.3.9.data/data/data/tor_ssl.log
pyzeek-0.3.9.data/data/data/weird.log
pyzeek-0.3.9.data/data/data/x509.log
pyzeek-0.3.9.data/data/examples/anomaly_detection.py
pyzeek-0.3.9.data/data/examples/anomaly_detection_streaming.py
pyzeek-0.3.9.dist-info/LICENSE
pyzeek-0.3.9.dist-info/METADATA
pyzeek-0.3.9.dist-info/WHEEL
pyzeek-0.3.9.dist-info/top_level.txt
pyzeek-0.3.9.dist-info/RECORD
