Metadata-Version: 2.1
Name: pyzeek
Version: 0.3.9
Summary: Zeek Analysis Tools
Home-page: https://github.com/SuperCowPowers/zat
Author: Brian Wylie
Author-email: briford@supercowpowers.com
License: Apache
Keywords: Zeek,Bro,Python,Networking,Security,Scikit-Learn,Spark,Kafka,Parquet
Platform: UNKNOWN
Classifier: Development Status :: 2 - Pre-Alpha
Classifier: Intended Audience :: Developers
Classifier: License :: OSI Approved :: Apache Software License
Classifier: Natural Language :: English
Classifier: Programming Language :: Python :: 2.7
Classifier: Programming Language :: Python :: 3.6
Classifier: Programming Language :: Python :: 3.7
Classifier: Programming Language :: Python :: Implementation :: CPython
Classifier: Programming Language :: Python :: Implementation :: PyPy
Requires-Dist: requests
Requires-Dist: watchdog
Requires-Dist: numpy
Requires-Dist: scipy
Requires-Dist: pandas
Requires-Dist: scikit-learn
Requires-Dist: pyspark
Requires-Dist: pyarrow
Provides-Extra: all
Requires-Dist: yara-python ; extra == 'all'
Requires-Dist: tldextract ; extra == 'all'
